setup.py
dsnd_distributions_project/Binomialdistribution.py
dsnd_distributions_project/Gaussiandistribution.py
dsnd_distributions_project/Generaldistribution.py
dsnd_distributions_project/__init__.py
dsnd_distributions_project.egg-info/PKG-INFO
dsnd_distributions_project.egg-info/SOURCES.txt
dsnd_distributions_project.egg-info/dependency_links.txt
dsnd_distributions_project.egg-info/not-zip-safe
dsnd_distributions_project.egg-info/top_level.txt