Metadata-Version: 1.0
Name: dsnd-distributions-project
Version: 0.1
Summary: Gaussian & Binoamial distributions
Home-page: UNKNOWN
Author: Eduardo Gonzalez
Author-email: gonzandrobles@gmail.com
License: UNKNOWN
Platform: UNKNOWN
